Workbook

Sheet Risk Register
A1: INTERNAL RISK REGISTER
A2: Enterprise Risk Management — Confidential
A4: Total Risks | C4: Critical / High | E4: Medium | G4: Low | I4: Open | K4: In Progress | M4: Closed | O4: Avg Risk Score
A5: =COUNTA(A8:A57) -> 50 | C5: =COUNTIF(K8:K57,"Critical")+COUNTIF(K8:K57,"High") -> 29 | E5: =COUNTIF(K8:K57,"Medium") -> 21 | G5: =COUNTIF(K8:K57,"Low") -> 0 | I5: =COUNTIF(N8:N57,"Open") -> 26 | K5: =COUNTIF(N8:N57,"In Progress") -> 20 | M5: =COUNTIF(N8:N57,"Closed") -> 4 | O5: =IFERROR(AVERAGE(J8:J57),"-") -> 11.16
A7: Risk ID | B7: Risk Category | C7: Sub-Category | D7: Risk Title | E7: Risk Description | F7: Risk Owner | G7: Department | H7: Likelihood (1–5) | I7: Impact (1–5) | J7: Risk Score | K7: Risk Level | L7: Inherent Risk | M7: Control Description | N7: Status | O7: Target Date | P7: Residual Risk | Q7: Last Reviewed | R7: Notes
A8: RSK-001 | B8: Operational | C8: Process Failure | D8: Critical Process Breakdown | E8: Key operational processes lack documented procedures and backups, risking service disruption | F8: COO | G8: Operations | H8: 4 | I8: 4 | J8: =H8*I8 -> 16 | K8: High | L8: High | M8: SOPs documented; quarterly process audits | N8: Open | O8: 2026-03-31 | P8: Medium | Q8: 2026-01-15 | R8: Priority remediation item
A9: RSK-002 | B9: Operational | C9: Human Error | D9: Data Entry Errors | E9: Manual data entry processes result in inaccurate records impacting business decisions | F9: Ops Manager | G9: Operations | H9: 4 | I9: 3 | J9: =H9*I9 -> 12 | K9: High | L9: High | M9: Input validation controls; dual-entry checks | N9: In Progress | O9: 2026-02-28 | P9: Medium | Q9: 2026-01-15 | R9: Automation in progress
A10: RSK-003 | B10: Operational | C10: Vendor Management | D10: Third-Party Vendor Failure | E10: Reliance on single-source vendors creates operational continuity risk | F10: Procurement Dir | G10: Procurement | H10: 3 | I10: 4 | J10: =H10*I10 -> 12 | K10: High | L10: High | M10: Vendor diversification; SLA enforcement | N10: Open | O10: 2026-06-30 | P10: Medium | Q10: 2026-01-15 | R10: Vendor audit scheduled Q2
A11: RSK-004 | B11: Operational | C11: Capacity Planning | D11: Resource Constraints | E11: Insufficient staffing during peak periods leads to service degradation | F11: HR Director | G11: Human Resources | H11: 3 | I11: 3 | J11: =H11*I11 -> 9 | K11: Medium | L11: Medium | M11: Seasonal hiring plan; cross-training | N11: In Progress | O11: 2026-04-15 | P11: Medium | Q11: 2026-01-15 | R11: Headcount review underway
A12: RSK-005 | B12: Operational | C12: Change Management | D12: Uncontrolled Change Implementation | E12: System or process changes deployed without adequate testing or rollback plans | F12: IT Director | G12: IT | H12: 4 | I12: 4 | J12: =H12*I12 -> 16 | K12: High | L12: High | M12: Change advisory board; staged rollouts | N12: Open | O12: 2026-02-15 | P12: Medium | Q12: 2026-01-15 | R12: CAB policy being drafted
A13: RSK-006 | B13: Financial | C13: Budget Overrun | D13: Project Cost Escalation | E13: Projects consistently exceed approved budgets due to poor estimation and scope creep | F13: CFO | G13: Finance | H13: 4 | I13: 3 | J13: =H13*I13 -> 12 | K13: High | L13: High | M13: Stage-gate approvals; budget variance reporting | N13: In Progress | O13: 2026-03-01 | P13: Medium | Q13: 2026-01-15 | R13: Monthly budget reviews instituted
A14: RSK-007 | B14: Financial | C14: Fraud | D14: Internal Fraud & Misappropriation | E14: Inadequate segregation of duties creates opportunity for internal financial fraud | F14: CFO | G14: Finance | H14: 2 | I14: 5 | J14: =H14*I14 -> 10 | K14: High | L14: High | M14: Dual approval workflows; internal audit program | N14: Open | O14: 2026-01-31 | P14: Medium | Q14: 2026-01-15 | R14: Segregation of duties review due
A15: RSK-008 | B15: Financial | C15: Liquidity | D15: Cash Flow Shortfall | E15: Unexpected revenue dips or delayed receivables could impair near-term liquidity | F15: Treasurer | G15: Finance | H15: 3 | I15: 4 | J15: =H15*I15 -> 12 | K15: High | L15: High | M15: Rolling 13-week cash forecast; credit facility | N15: Open | O15: 2026-03-15 | P15: Medium | Q15: 2026-01-15 | R15: Cash model updated monthly
A16: RSK-009 | B16: Financial | C16: FX Exposure | D16: Foreign Currency Risk | E16: International transactions expose the company to adverse currency fluctuations | F16: CFO | G16: Finance | H16: 3 | I16: 3 | J16: =H16*I16 -> 9 | K16: Medium | L16: Medium | M16: FX hedging policy; natural hedging | N16: Closed | O16: 2025-12-31 | P16: Low | Q16: 2026-01-15 | R16: Hedging program active
A17: RSK-010 | B17: Financial | C17: Tax Compliance | D17: Transfer Pricing Non-Compliance | E17: Intercompany transactions may not meet arm's-length transfer pricing standards | F17: Tax Director | G17: Finance | H17: 2 | I17: 4 | J17: =H17*I17 -> 8 | K17: Medium | L17: Medium | M17: Annual TP study; Big 4 advisor review | N17: In Progress | O17: 2026-06-30 | P17: Medium | Q17: 2026-01-15 | R17: TP documentation update in progress
A18: RSK-011 | B18: Technology | C18: Cybersecurity | D18: Ransomware Attack | E18: Phishing or unpatched systems could allow ransomware to encrypt critical data | F18: CISO | G18: IT Security | H18: 4 | I18: 5 | J18: =H18*I18 -> 20 | K18: Critical | L18: Critical | M18: EDR tooling; immutable backups; user training | N18: Open | O18: 2026-01-31 | P18: Medium | Q18: 2026-01-15 | R18: Tabletop exercise Q1 2026
A19: RSK-012 | B19: Technology | C19: Cybersecurity | D19: Insider Threat | E19: Privileged users may intentionally or accidentally exfiltrate sensitive data | F19: CISO | G19: IT Security | H19: 3 | I19: 4 | J19: =H19*I19 -> 12 | K19: High | L19: High | M19: UEBA monitoring; least-privilege access | N19: In Progress | O19: 2026-03-01 | P19: Medium | Q19: 2026-01-15 | R19: DLP deployment ongoing
... A58: RSK-051 | B58: Operational | C58: Facilities | D58: Critical Facilities Failure | E58: HVAC, power, or physical security failures at key sites disrupt operations | F58: Facilities Mgr | G58: Facilities | H58: 2 | I58: 4 | J58: =H58*I58 -> 8 | K58: Medium | L58: Medium | M58: Preventive maintenance schedule; backup generators | N58: Closed | O58: 2025-10-31 | P58: Low | Q58: 2026-01-15 | R58: UPS and generators tested

Sheet Risk Matrix
A1: RISK HEAT MAP — LIKELIHOOD vs IMPACT
A2: Scores = Likelihood × Impact | Max Score = 25
B4: Impact 1 Negligible | C4: Impact 2 Minor | D4: Impact 3 Moderate | E4: Impact 4 Major | F4: Impact 5 Critical
A5: Likelihood 5 Almost Certain | B5: 5 | C5: 10 | D5: 15 | E5: 20 | F5: 25
A6: Likelihood 4 Likely | B6: 4 | C6: 8 | D6: 12 | E6: 16 | F6: 20
A7: Likelihood 3 Possible | B7: 3 | C7: 6 | D7: 9 | E7: 12 | F7: 15
A8: Likelihood 2 Unlikely | B8: 2 | C8: 4 | D8: 6 | E8: 8 | F8: 10
A9: Likelihood 1 Rare | B9: 1 | C9: 2 | D9: 3 | E9: 4 | F9: 5
A12: CRITICAL / HIGH (Score 15–25)
A13: MEDIUM (Score 8–12)
A14: LOW (Score 1–6)

Sheet Scoring Guide
A1: RISK SCORING GUIDE
A3: LIKELIHOOD SCALE
A4: 1 – Rare | C4: Event unlikely to occur; < once every 5 years | D4: < 5%
A5: 2 – Unlikely | C5: Event could occur but not expected; 1–3 years | D5: 5–25%
A6: 3 – Possible | C6: Event may occur in some circumstances; 1–2 years | D6: 26–50%
A7: 4 – Likely | C7: Event will probably occur in most circumstances; < 1 year | D7: 51–75%
A8: 5 – Almost Certain | C8: Event expected to occur in most circumstances; within months | D8: 76–100%
A10: IMPACT SCALE
A11: 1 – Negligible | C11: Minimal impact; easily absorbed; no disruption to objectives
A12: 2 – Minor | C12: Minor impact; short-term disruption; < $10K financial loss
A13: 3 – Moderate | C13: Moderate impact; recoverable within weeks; $10K–$100K loss
A14: 4 – Major | C14: Significant impact; recovery may take months; $100K–$1M loss
A15: 5 – Critical | C15: Catastrophic impact; threatens viability; > $1M loss
A17: RISK RATING MATRIX
A18: Critical | B18: 20–25 | C18: Immediate executive action required; board notification
A19: High | B19: 15–19 | C19: Senior management action; formal risk treatment plan
A20: Medium | B20: 8–12 | C20: Management responsibility; mitigation plan required
A21: Low | B21: 1–6 | C21: Routine monitoring; manage through standard procedures
A24: RISK CATEGORIES
A25: Operational | C25: Process failures, vendor issues, human error, capacity
A26: Financial | C26: Fraud, budget overrun, liquidity, FX, tax
A27: Technology | C27: Cybersecurity, infrastructure, cloud, AI/ML, APIs
A28: Compliance | C28: Regulatory, contractual, anti-bribery, licensing
A29: Strategic | C29: Market, M&A, innovation, concentration, reputation
A30: People | C30: Talent, culture, H&S, remote work, DEI
A31: Environmental | C31: Climate, ESG reporting, waste management
A32: Legal | C32: Litigation, IP, product liability, privacy
A33: Supply Chain | C33: Disruption, logistics, geopolitical trade risk

Sheet Dashboard
A1: RISK MANAGEMENT DASHBOARD
A2: Summary view — linked to Risk Register
A4: Total Risks | C4: Critical | E4: High | G4: Medium
A5: ='Risk Register'!A5 -> 50 | C5: =COUNTIF('Risk Register'!K8:K57,"Critical") -> 1 | E5: =COUNTIF('Risk Register'!K8:K57,"High") -> 28 | G5: =COUNTIF('Risk Register'!K8:K57,"Medium") -> 21
A7: Open Risks | C7: In Progress | E7: Closed | G7: Avg Score
A8: =COUNTIF('Risk Register'!N8:N57,"Open") -> 26 | C8: =COUNTIF('Risk Register'!N8:N57,"In Progress") -> 20 | E8: =COUNTIF('Risk Register'!N8:N57,"Closed") -> 4 | G8: =IFERROR(AVERAGE('Risk Register'!J8:J57),"-") -> 11.16
A11: RISKS BY CATEGORY
A12: Operational | B12: =COUNTIF('Risk Register'!B8:B57,"Operational") -> 6 | C12: =IFERROR(B12/'Risk Register'!A5,0) -> 0.12
A13: Financial | B13: =COUNTIF('Risk Register'!B8:B57,"Financial") -> 6 | C13: =IFERROR(B13/'Risk Register'!A5,0) -> 0.12
A14: Technology | B14: =COUNTIF('Risk Register'!B8:B57,"Technology") -> 10 | C14: =IFERROR(B14/'Risk Register'!A5,0) -> 0.2
A15: Compliance | B15: =COUNTIF('Risk Register'!B8:B57,"Compliance") -> 6 | C15: =IFERROR(B15/'Risk Register'!A5,0) -> 0.12
A16: Strategic | B16: =COUNTIF('Risk Register'!B8:B57,"Strategic") -> 6 | C16: =IFERROR(B16/'Risk Register'!A5,0) -> 0.12
A17: People | B17: =COUNTIF('Risk Register'!B8:B57,"People") -> 6 | C17: =IFERROR(B17/'Risk Register'!A5,0) -> 0.12
A18: Environmental | B18: =COUNTIF('Risk Register'!B8:B57,"Environmental") -> 3 | C18: =IFERROR(B18/'Risk Register'!A5,0) -> 0.06
A19: Legal | B19: =COUNTIF('Risk Register'!B8:B57,"Legal") -> 4 | C19: =IFERROR(B19/'Risk Register'!A5,0) -> 0.08
A20: Supply Chain | B20: =COUNTIF('Risk Register'!B8:B57,"Supply Chain") -> 3 | C20: =IFERROR(B20/'Risk Register'!A5,0) -> 0.06
